{
  "lexicon": 1,
  "id": "org.hypercerts.claim.evidence",
  "defs": {
    "main": {
      "type": "record",
      "description": "A piece of evidence supporting a hypercert claim",
      "key": "any",
      "record": {
        "type": "object",
        "required": ["content", "shortDescription", "createdAt"],
        "properties": {
          "content": {
            "type": "union",
            "refs": ["app.certified.defs#uri", "app.certified.defs#smallBlob"],
            "description": "A piece of evidence (URI or blobs) supporting a hypercert claim"
          },
          "title": {
            "type": "string",
            "maxLength": 256,
            "description": "Optional title to describe the nature of the evidence"
          },
          "shortDescription": {
            "type": "string",
            "maxLength": 3000,
            "maxGraphemes": 300,
            "description": "Short description explaining what this evidence demonstrates or proves"
          },
          "description": {
              "type": "string",
              "description": "Optional longer description describing the impact claim evidence.",
              "maxLength": 30000,
              "maxGraphemes": 3000
          },
          "createdAt": {
              "type": "string",
              "format": "datetime",
              "description": "Client-declared timestamp when this hypercert claim was originally created"
            }
        }
      }
    }
  }
}